pychain/__init__.py
pychain/chainable.py
pychain/common.py
pychain/enum.py
pychain/pipeline.py
pychainable-0.1.2.dist-info/LICENSE
pychainable-0.1.2.dist-info/METADATA
pychainable-0.1.2.dist-info/WHEEL
pychainable-0.1.2.dist-info/top_level.txt
pychainable-0.1.2.dist-info/RECORD
