Metadata-Version: 2.2
Name: pyChainable
Version: 0.1.2
Summary: A package for creating chainable method calls in Python
Author-email: mrwuliu <mr_wuliu@foxmail.com>
Project-URL: Homepage, https://github.com/mr-wuliu/PythonChainable
Project-URL: Issues, https://github.com/mr-wuliu/PythonChainable/issues
Classifier: Programming Language :: Python :: 3
Classifier: License :: OSI Approved :: MIT License
Classifier: Operating System :: OS Independent
Requires-Python: >=3.10
License-File: LICENSE
